LICENSE
MANIFEST.in
README.rst
setup.cfg
setup.py
fulfil_shop_flipgive/__init__.py
fulfil_shop_flipgive/models.py
fulfil_shop_flipgive/signals.py
fulfil_shop_flipgive/views.py
fulfil_shop_flipgive.egg-info/PKG-INFO
fulfil_shop_flipgive.egg-info/SOURCES.txt
fulfil_shop_flipgive.egg-info/dependency_links.txt
fulfil_shop_flipgive.egg-info/not-zip-safe
fulfil_shop_flipgive.egg-info/top_level.txt