Metadata-Version: 1.1
Name: fulfil-shop-flipgive
Version: 0.1.8
Summary: Flip Give Extension for Flip Give.
Home-page: https://github.com/fulfilio/fulfil_shop_flipgive
Author: Fulfil.io
Author-email: info@fulfil.io
License: BSD license
Keywords: fulfil_shop_flipgive
Platform: UNKNOWN
Classifier: Development Status :: 2 - Pre-Alpha
Classifier: Intended Audience :: Developers
Classifier: License :: OSI Approved :: BSD License
Classifier: Natural Language :: English
Classifier: Programming Language :: Python :: 2
Classifier: Programming Language :: Python :: 2.6
Classifier: Programming Language :: Python :: 2.7
Classifier: Programming Language :: Python :: 3
Classifier: Programming Language :: Python :: 3.3
Classifier: Programming Language :: Python :: 3.4
Classifier: Programming Language :: Python :: 3.5
